ohtaylor/__init__.py
ohtaylor/diffcalc.py
ohtaylor/taylor.py
ohtaylor/taylornum.py
ohtaylor/taylorsym.py
ohtaylor/taylorutils.py
ohtaylor-1.1.0.dist-info/LICENSE
ohtaylor-1.1.0.dist-info/METADATA
ohtaylor-1.1.0.dist-info/WHEEL
ohtaylor-1.1.0.dist-info/top_level.txt
ohtaylor-1.1.0.dist-info/RECORD
